code_to_pdf/__init__.py
code_to_pdf/__main__.py
code_to_pdf/html_generator.py
code_to_pdf/pdf_generator.py
code_to_pdf/run.py
code_to_pdf/template.html
code_to_pdf/toc_generator.py
code_to_pdf/tree_generator.py
code_to_pdf-0.5.dist-info/LICENSE
code_to_pdf-0.5.dist-info/METADATA
code_to_pdf-0.5.dist-info/WHEEL
code_to_pdf-0.5.dist-info/entry_points.txt
code_to_pdf-0.5.dist-info/top_level.txt
code_to_pdf-0.5.dist-info/RECORD
