Metadata-Version: 2.1
Name: code-to-pdf
Version: 0.5
Summary: This convert a software proyect to a pdf book
Author-email: Isidro Arias <isidroariass@hotmail.es>
Project-URL: Homepage, https://github.com/isidroas/code_to_pdf
Project-URL: Bug Tracker, https://github.com/isidroas/code_to_pdf/issues
Classifier: Programming Language :: Python :: 3
Classifier: License :: OSI Approved :: MIT License
Classifier: Operating System :: OS Independent
Requires-Python: >=3.6
License-File: LICENSE
Requires-Dist: pygments
Requires-Dist: pdfkit
Requires-Dist: PyPDF2
Requires-Dist: reportlab
Requires-Dist: jinja2
Requires-Dist: art
Requires-Dist: gitpython
Requires-Dist: pyyaml
Provides-Extra: dev
Requires-Dist: mypy ; extra == 'dev'
Requires-Dist: black ; extra == 'dev'
Requires-Dist: pylint ; extra == 'dev'
Requires-Dist: coverage ; extra == 'dev'
Requires-Dist: types-PyYAML ; extra == 'dev'
Requires-Dist: pre-commit ; extra == 'dev'
